odoo10_addon_l10n_fr_intrastat_product-10.0.1.0.0.99.dev29-py3.8-nspkg.pth
odoo/addons/l10n_fr_intrastat_product/README.rst
odoo/addons/l10n_fr_intrastat_product/__init__.py
odoo/addons/l10n_fr_intrastat_product/__manifest__.py
odoo/addons/l10n_fr_intrastat_product/post_install.py
odoo/addons/l10n_fr_intrastat_product/data/deb.xsd
odoo/addons/l10n_fr_intrastat_product/data/intrastat_product_reminder.xml
odoo/addons/l10n_fr_intrastat_product/data/intrastat_transaction.xml
odoo/addons/l10n_fr_intrastat_product/demo/intrastat_demo.xml
odoo/addons/l10n_fr_intrastat_product/i18n/am.po
odoo/addons/l10n_fr_intrastat_product/i18n/bg.po
odoo/addons/l10n_fr_intrastat_product/i18n/ca.po
odoo/addons/l10n_fr_intrastat_product/i18n/da.po
odoo/addons/l10n_fr_intrastat_product/i18n/de.po
odoo/addons/l10n_fr_intrastat_product/i18n/el_GR.po
odoo/addons/l10n_fr_intrastat_product/i18n/es.po
odoo/addons/l10n_fr_intrastat_product/i18n/es_ES.po
odoo/addons/l10n_fr_intrastat_product/i18n/es_MX.po
odoo/addons/l10n_fr_intrastat_product/i18n/fi.po
odoo/addons/l10n_fr_intrastat_product/i18n/fr.po
odoo/addons/l10n_fr_intrastat_product/i18n/fr_CH.po
odoo/addons/l10n_fr_intrastat_product/i18n/gl.po
odoo/addons/l10n_fr_intrastat_product/i18n/hr.po
odoo/addons/l10n_fr_intrastat_product/i18n/it.po
odoo/addons/l10n_fr_intrastat_product/i18n/l10n_fr_intrastat_product.pot
odoo/addons/l10n_fr_intrastat_product/i18n/nb_NO.po
odoo/addons/l10n_fr_intrastat_product/i18n/nl.po
odoo/addons/l10n_fr_intrastat_product/i18n/pt.po
odoo/addons/l10n_fr_intrastat_product/i18n/pt_BR.po
odoo/addons/l10n_fr_intrastat_product/i18n/pt_PT.po
odoo/addons/l10n_fr_intrastat_product/i18n/sl.po
odoo/addons/l10n_fr_intrastat_product/i18n/tr.po
odoo/addons/l10n_fr_intrastat_product/models/__init__.py
odoo/addons/l10n_fr_intrastat_product/models/account_config_settings.py
odoo/addons/l10n_fr_intrastat_product/models/company.py
odoo/addons/l10n_fr_intrastat_product/models/intrastat_product.py
odoo10_addon_l10n_fr_intrastat_product-10.0.1.0.0.99.dev29.dist-info/METADATA
odoo10_addon_l10n_fr_intrastat_product-10.0.1.0.0.99.dev29.dist-info/WHEEL
odoo10_addon_l10n_fr_intrastat_product-10.0.1.0.0.99.dev29.dist-info/namespace_packages.txt
odoo10_addon_l10n_fr_intrastat_product-10.0.1.0.0.99.dev29.dist-info/top_level.txt
odoo10_addon_l10n_fr_intrastat_product-10.0.1.0.0.99.dev29.dist-info/RECORD
