Metadata-Version: 2.1
Name: odoo10-addon-l10n-fr-intrastat-product
Version: 10.0.1.0.0.99.dev29
Summary: DEB (Déclaration d'Échange de Biens) for France
Home-page: http://www.akretion.com
Author: Akretion,Odoo Community Association (OCA)
Author-email: support@odoo-community.org
License: AGPL-3
Platform: UNKNOWN
Classifier: Programming Language :: Python
Classifier: Framework :: Odoo
Classifier: Framework :: Odoo :: 10.0
Classifier: License :: OSI Approved :: GNU Affero General Public License v3
Requires-Python: ~=2.7
Requires-Dist: odoo10-addon-intrastat-product
Requires-Dist: odoo10-addon-l10n-fr-department
Requires-Dist: odoo10-addon-l10n-fr-siret
Requires-Dist: odoo (<10.1dev,>=10.0)
